{"last_update":"2026-06-04T08:43:07Z","data":[{"formation":1780562253902,"id":1128,"speed":0.1227617,"notch":-4,"modelName":"ASTA_ATKtypeH_b1","isControlCar":true,"signal":0,"driver":"BlockFT","passengers":[null,null,null,null,null,null,null,null],"pos":{"x":-12322.673811943732,"y":66.25,"z":11414.457320473926},"trainStateData":[0,-4,0,0,0,2,1,0,0,0,0,0,0,0,0,0],"name":"no_name","customButton":[]},{"formation":1780562253902,"id":1139,"speed":0.1227617,"notch":-8,"modelName":"ASTA_ATKtypeH_b2","isControlCar":false,"signal":0,"driver":"","passengers":[null,null,null,null,null,null,null,null,null,null,null,null,null],"pos":{"x":-12318.189959185638,"y":66.25,"z":11411.465902813285},"trainStateData":[0,-8,0,0,0,2,1,0,0,0,1,0,0,0,0,0],"name":"no_name","customButton":[]},{"formation":1780562253902,"id":1155,"speed":0.1227617,"notch":-8,"modelName":"ASTA_ATKtypeH_b3","isControlCar":false,"signal":0,"driver":"","passengers":[null,null,null,null,null,null,null,null],"pos":{"x":-12313.703067589813,"y":66.25,"z":11408.479053012808},"trainStateData":[1,-8,0,0,0,2,1,0,0,0,1,0,0,0,0,0],"name":"no_name","customButton":[]}]}