{"last_update":"2026-04-19T07:03:28Z","data":[{"formation":1776581410907,"id":40989,"speed":0.0,"notch":-8,"modelName":"KH6000Tc","isControlCar":false,"signal":0,"driver":"","passengers":[null,null,null,null,null,null,null,null,null,null,null,null,null,null,null,null,null,null,null,null,null,null,null,null,null,null,null,null,null,null,null,null,null,null,null,null,null,null,null,null],"pos":{"x":-8473.061128103513,"y":66.25,"z":11494.819111028048},"trainStateData":[1,-8,0,0,0,2,0,0,0,2,1,0,0,0,0,0],"name":"no_name","customButton":[]},{"formation":1776581410907,"id":41078,"speed":0.0,"notch":-8,"modelName":"KH6000M2","isControlCar":false,"signal":0,"driver":"","passengers":[null,null,null,null,null,null,null,null,null,null,null,null,null,null,null,null,null,null,null,null,null,null,null,null,null,null,null,null,null,null,null,null,null,null,null,null,null,null,null,null],"pos":{"x":-8453.08314811636,"y":66.25,"z":11493.767565986163},"trainStateData":[1,-8,0,0,0,2,0,0,0,2,1,0,0,0,0,0],"name":"no_name","customButton":[]},{"formation":1776581410907,"id":41121,"speed":0.0,"notch":-8,"modelName":"KH6000M","isControlCar":false,"signal":0,"driver":"","passengers":[null,null,null,null,null,null,null,null,null,null,null,null,null,null,null,null,null,null,null,null,null,null,null,null,null,null,null,null,null,null,null,null,null,null,null,null,null,null,null,null],"pos":{"x":-8433.104901389914,"y":66.25,"z":11492.716073957887},"trainStateData":[1,-8,0,0,0,2,0,0,0,2,1,0,0,0,0,0],"name":"no_name","customButton":[]},{"formation":1776581410907,"id":41165,"speed":0.0,"notch":-8,"modelName":"KH6000T","isControlCar":false,"signal":0,"driver":"","passengers":[null,null,null,null,null,null,null,null,null,null,null,null,null,null,null,null,null,null,null,null,null,null,null,null,null,null,null,null,null,null,null,null,null,null,null,null,null,null,null,null],"pos":{"x":-8413.126635886441,"y":66.25,"z":11491.664689592018},"trainStateData":[1,-8,0,0,0,2,0,0,0,2,1,0,0,0,0,0],"name":"no_name","customButton":[]},{"formation":1776581410907,"id":41208,"speed":0.0,"notch":-5,"modelName":"KH6000Mc","isControlCar":true,"signal":0,"driver":"","passengers":[null,null,null,null,null,null,null,null,null,null,null,null,null,null,null,null,null,null,null,null,null,null,null,null,null,null,null,null,null,null,null,null,null,null,null,null,null,null,null,null],"pos":{"x":-8393.14860973458,"y":66.25,"z":11490.6129988545},"trainStateData":[0,-5,0,0,0,2,0,0,0,2,0,0,0,0,0,0],"name":"no_name","customButton":[]},{"formation":1776582105819,"id":41618,"speed":0.006997654,"notch":-6,"modelName":"g91A1030","isControlCar":false,"signal":0,"driver":"","passengers":[null,null,null,null,null,null,null,null,null,null,null,null,null,null,null,null,null,null,null,null,null,null,null,null,null,null,null,null],"pos":{"x":-18340.156745077154,"y":69.30139695480466,"z":-16846.09603947705},"trainStateData":[0,-6,0,0,0,0,1,0,0,0,1,0,0,0,0,0],"name":"no_name","customButton":[{"value":1,"text":"ヘッド入"},{"value":0,"text":"テール切"},{"value":0,"text":"無地"},{"value":0,"text":"1"},{"value":0,"text":"ワイパ切"},{"value":0,"text":"日除け切"}]},{"formation":1776582105819,"id":41668,"speed":0.006997654,"notch":-8,"modelName":"g93A1030","isControlCar":false,"signal":0,"driver":"","passengers":[null,null,null,null,null,null,null,null,null,null,null,null,null,null,null,null,null,null,null,null,null,null,null,null,null,null,null,null],"pos":{"x":-18343.335721544863,"y":69.32650372758508,"z":-16865.839246449144},"trainStateData":[0,-8,0,0,0,0,1,0,0,0,1,0,0,0,0,0],"name":"no_name","customButton":[{"value":0,"text":"ヘッド切"},{"value":0,"text":"テール切"},{"value":0,"text":"無地"},{"value":0,"text":"101"}]},{"formation":1776582105819,"id":41699,"speed":0.006997654,"notch":-8,"modelName":"g94A1030","isControlCar":false,"signal":0,"driver":"","passengers":[null,null,null,null,null,null,null,null,null,null,null,null,null,null,null,null,null,null,null,null,null,null,null,null,null,null,null,null],"pos":{"x":-18347.750682826765,"y":69.3385813087225,"z":-16885.343910702457},"trainStateData":[1,-8,0,0,0,0,1,0,0,0,1,0,0,0,0,0],"name":"no_name","customButton":[{"value":0,"text":"ヘッド切"},{"value":0,"text":"テール切"},{"value":0,"text":"無地"},{"value":0,"text":"101"},{"value":0,"text":"ワイパ切"},{"value":0,"text":"日除け切"}]},{"formation":1776582105819,"id":41730,"speed":0.006997654,"notch":-8,"modelName":"g91A1030","isControlCar":false,"signal":0,"driver":"","passengers":[null,null,null,null,null,null,null,null,null,null,null,null,null,null,null,null,null,null,null,null,null,null,null,null,null,null,null,null],"pos":{"x":-18353.407489187382,"y":69.32113185152411,"z":-16904.512030894977},"trainStateData":[0,-8,0,0,0,0,1,0,0,0,1,0,0,0,0,0],"name":"no_name","customButton":[{"value":0,"text":"ヘッド切"},{"value":0,"text":"テール切"},{"value":0,"text":"無地"},{"value":0,"text":"1"},{"value":0,"text":"ワイパ切"},{"value":0,"text":"日除け切"}]},{"formation":1776582105819,"id":41761,"speed":0.006997654,"notch":-8,"modelName":"g93A1030","isControlCar":true,"signal":0,"driver":"H1rase","passengers":[null,null,null,null,null,null,null,null,null,null,null,null,null,null,null,null,null,null,null,null,null,null,null,null,null,null,null,null],"pos":{"x":-18360.257502671873,"y":69.3009100407362,"z":-16923.285201089522},"trainStateData":[0,-8,0,0,0,0,1,0,0,0,0,0,0,0,0,0],"name":"no_name","customButton":[{"value":0,"text":"ヘッド切"},{"value":0,"text":"テール切"},{"value":0,"text":"無地"},{"value":0,"text":"101"}]},{"formation":1776582105819,"id":41793,"speed":0.006997654,"notch":-8,"modelName":"g94A1030","isControlCar":false,"signal":0,"driver":"","passengers":[null,null,null,null,null,null,null,null,null,null,null,null,null,null,null,null,null,null,null,null,null,null,null,null,null,null,null,null],"pos":{"x":-18368.24067690533,"y":69.28066450729966,"z":-16941.609891268625},"trainStateData":[1,-8,0,0,0,0,1,0,0,0,1,0,0,0,0,0],"name":"no_name","customButton":[{"value":0,"text":"ヘッド切"},{"value":0,"text":"テール切"},{"value":0,"text":"無地"},{"value":0,"text":"101"},{"value":0,"text":"ワイパ切"},{"value":0,"text":"日除け切"}]},{"formation":1776582192190,"id":41833,"speed":0.0,"notch":0,"modelName":"kit_KL-MP35JM","isControlCar":true,"signal":0,"driver":"","passengers":[null,null,null,null,null,null,null,null,null,null,null,null,null,null,null,null],"pos":{"x":-12446.515625657048,"y":66.25,"z":12154.5},"trainStateData":[0,0,0,0,0,0,0,0,0,0,0,0,0,0,0,0],"name":"no_name","customButton":[{"value":0,"text":"デイライトoff"},{"value":0,"text":"車いすoff"},{"value":0,"text":"ロービーム"}]}]}