{"last_update":"2026-04-18T02:50:12Z","data":[{"formation":1776480483771,"id":1211,"speed":1.55294,"notch":-8,"modelName":"Minaoka 811 re","isControlCar":false,"signal":0,"driver":"","passengers":[null,null,null,null,null,null,null,null,null,null,null,null,null,null,null,null,null,null,null,null,null,null,null,null,null,null,null,null],"pos":{"x":592.9218721306195,"y":76.25,"z":10860.50626713004},"trainStateData":[0,-8,0,0,0,2,0,0,0,0,1,0,0,0,0,0],"name":"no_name","customButton":[]},{"formation":1776480483771,"id":1273,"speed":1.55294,"notch":0,"modelName":"Minaoka 851 re","isControlCar":true,"signal":0,"driver":"BlockFT","passengers":[null,null,null,null,null,null,null,null,null,null,null,null,null,null,null,null,null,null,null,null,null,null,null,null,null,null,null,null],"pos":{"x":572.9218744070167,"y":76.25,"z":10860.506003478135},"trainStateData":[0,0,0,0,0,2,0,0,0,0,0,0,0,0,0,0],"name":"no_name","customButton":[]},{"formation":1776480483771,"id":1311,"speed":1.55294,"notch":-8,"modelName":"Minaoka 821 Re","isControlCar":false,"signal":0,"driver":"","passengers":[null,null,null,null,null,null,null,null,null,null,null,null,null,null,null,null,null,null,null,null,null,null,null,null,null,null,null,null],"pos":{"x":612.9218726956885,"y":76.25,"z":10860.505440219293},"trainStateData":[1,-8,0,0,0,2,0,0,0,0,1,0,0,0,0,0],"name":"no_name","customButton":[]}]}