{"last_update":"2026-04-10T14:54:34Z","data":[{"formation":1775830164967,"id":501,"speed":0.3805384,"notch":-8,"modelName":"KH6000Tc","isControlCar":false,"signal":0,"driver":"","passengers":[null,null,null,null,null,null,null,null,null,null,null,null,null,null,null,null,null,null,null,null,null,null,null,null,null,null,null,null,null,null,null,null,null,null,null,null,null,null,null,null],"pos":{"x":-10059.762721477566,"y":66.25,"z":10497.5},"trainStateData":[1,-8,0,0,0,1,0,0,0,0,1,0,0,0,0,0],"name":"no_name","customButton":[]},{"formation":1775830164967,"id":544,"speed":0.3805384,"notch":-8,"modelName":"KH6000T","isControlCar":false,"signal":0,"driver":"","passengers":[null,null,null,null,null,null,null,null,null,null,null,null,null,null,null,null,null,null,null,null,null,null,null,null,null,null,null,null,null,null,null,null,null,null,null,null,null,null,null,null],"pos":{"x":-10079.76415511913,"y":66.25,"z":10497.5},"trainStateData":[1,-8,0,0,0,1,0,0,0,0,1,0,0,0,0,0],"name":"no_name","customButton":[]},{"formation":1775830164967,"id":587,"speed":0.3805384,"notch":-8,"modelName":"KH6000M","isControlCar":false,"signal":0,"driver":"","passengers":[null,null,null,null,null,null,null,null,null,null,null,null,null,null,null,null,null,null,null,null,null,null,null,null,null,null,null,null,null,null,null,null,null,null,null,null,null,null,null,null],"pos":{"x":-10099.765805516705,"y":66.25,"z":10497.5},"trainStateData":[1,-8,0,0,0,1,0,0,0,0,1,0,0,0,0,0],"name":"no_name","customButton":[]},{"formation":1775830164967,"id":630,"speed":0.3805384,"notch":-8,"modelName":"KH6000M2","isControlCar":false,"signal":0,"driver":"","passengers":[null,null,null,null,null,null,null,null,null,null,null,null,null,null,null,null,null,null,null,null,null,null,null,null,null,null,null,null,null,null,null,null,null,null,null,null,null,null,null,null],"pos":{"x":-10119.765711934944,"y":66.25,"z":10497.49802065498},"trainStateData":[1,-8,0,0,0,1,0,0,0,0,1,0,0,0,0,0],"name":"no_name","customButton":[]},{"formation":1775830164967,"id":673,"speed":0.3805384,"notch":4,"modelName":"KH6000Mc","isControlCar":true,"signal":0,"driver":"BlockFT","passengers":[null,null,null,null,null,null,null,null,null,null,null,null,null,null,null,null,null,null,null,null,null,null,null,null,null,null,null,null,null,null,null,null,null,null,null,null,null,null,null,null],"pos":{"x":-10139.778787283376,"y":66.25,"z":10497.493550480915},"trainStateData":[0,4,0,0,0,1,0,0,0,0,0,0,0,0,0,0],"name":"no_name","customButton":[]}]}