{"last_update":"2026-06-13T02:18:59Z","data":[{"formation":1781317068413,"id":1488,"speed":0.29906335,"notch":5,"modelName":"Hoshikage700_1_Mc","isControlCar":true,"signal":0,"driver":"BlockFT","passengers":[null,null,null,null,null,null,null,null,null,null,null,null,null,null,null,null,"eight8143","Ga_libe4104",null,null,null,null,null,null,null,null,null,null,null,null,null,null,null,null,null,null,null,null,null,null,null,null,null,null,null,null,null,null,null,null,null,null,null,null,null,null],"pos":{"x":15666.415306101355,"y":66.25,"z":-5850.5},"trainStateData":[0,5,0,0,0,2,0,0,1,0,0,0,0,0,0,0],"name":"no_name","customButton":[]},{"formation":1781317068413,"id":1831,"speed":0.29906335,"notch":-8,"modelName":"Hoshikage700_2_Tc","isControlCar":false,"signal":0,"driver":"","passengers":[null,null,null,null,null,null,null,null,null,null,null,null,null,null,null,null,null,null,null,null,null,null,null,null,null,null,null,null,null,null,null,null,null,null,null,null,null,null,null,null,null,null,null,null,null,null,null,null,null,null,null,null,null,null,null,null],"pos":{"x":15686.416695086666,"y":66.25,"z":-5850.5},"trainStateData":[1,-8,0,0,0,2,0,0,0,0,1,0,0,0,0,0],"name":"no_name","customButton":[]}]}