{"last_update":"2026-04-09T14:55:36Z","data":[{"formation":1775744909314,"id":3418,"speed":0.03957202,"notch":-8,"modelName":"MK683_E","isControlCar":false,"signal":0,"driver":"","passengers":[null,null,null,null,null,null,null,null,null,null,null,null,null,null,null,null,null,null,null,null,null,null,null,null],"pos":{"x":-14146.984817616802,"y":52.9375,"z":10750.95524437099},"trainStateData":[1,-8,0,0,0,2,1,0,0,0,1,1,0,0,0,0],"name":"no_name","customButton":[{"value":0,"text":"PT:W51"},{"value":6,"text":"種:はいたか"},{"value":0,"text":"行先:未実装"}]},{"formation":1775744909314,"id":3445,"speed":0.03957202,"notch":-8,"modelName":"MK683_G","isControlCar":false,"signal":0,"driver":"","passengers":[null,null,null,null,null,null,null,null,null,null,null,null,null,null,null,null,null,null,null,null,null,null,null,null,null,null,null,null,null,null,null,null],"pos":{"x":-14146.5,"y":52.9375,"z":10770.957910468433},"trainStateData":[1,-8,0,0,0,2,1,0,0,0,1,1,0,0,0,0],"name":"no_name","customButton":[{"value":0,"text":"PT:W51"},{"value":6,"text":"種:はいたか"},{"value":0,"text":"行先:未実装"}]},{"formation":1775744909314,"id":3480,"speed":0.03957202,"notch":-8,"modelName":"MK683_F","isControlCar":false,"signal":0,"driver":"","passengers":[null,null,null,null,null,null,null,null,null,null,null,null,null,null,null,null,null,null,null,null,null,null,null,null],"pos":{"x":-14146.5,"y":52.9375,"z":10790.958977448074},"trainStateData":[0,-8,0,0,0,2,1,0,0,0,1,1,0,0,0,0],"name":"no_name","customButton":[{"value":0,"text":"PT:W51"},{"value":6,"text":"種:はいたか"},{"value":0,"text":"行先:未実装"}]},{"formation":1775744909314,"id":3507,"speed":0.03957202,"notch":-8,"modelName":"MK683_E","isControlCar":false,"signal":0,"driver":"","passengers":[null,null,null,null,null,null,null,null,null,null,null,"eight8143",null,null,null,null,null,null,null,null,null,null,null,null],"pos":{"x":-14146.5,"y":52.9375,"z":10810.960829302465},"trainStateData":[1,-8,0,0,0,2,1,0,0,0,1,1,0,0,0,0],"name":"no_name","customButton":[{"value":0,"text":"PT:W51"},{"value":6,"text":"種:はいたか"},{"value":0,"text":"行先:未実装"}]},{"formation":1775744909314,"id":3534,"speed":0.03957202,"notch":-8,"modelName":"MK683_B","isControlCar":false,"signal":0,"driver":"","passengers":[null,null,null,null,null,null,null,null,null,null,null,null,null,null,null,null,null,null,null,null,null,null,null,null,null,null,null,null,null,null,null,null],"pos":{"x":-14146.5,"y":52.9375,"z":10830.96268115686},"trainStateData":[1,-8,0,0,0,2,1,0,0,0,1,1,0,0,0,0],"name":"no_name","customButton":[{"value":0,"text":"PT:W51"},{"value":6,"text":"種:はいたか"},{"value":0,"text":"行先:未実装"}]},{"formation":1775744909314,"id":3569,"speed":0.03957202,"notch":-8,"modelName":"MK683_D","isControlCar":false,"signal":0,"driver":"","passengers":[null,null,null,null,null,null,null,null,null,null,null,null,null,null,null,null,null,null,null,null,null,null,null,null,null,null,null,null,null,null,null,null],"pos":{"x":-14146.5,"y":52.9375,"z":10850.96453351789},"trainStateData":[0,-8,0,0,0,2,1,0,0,0,1,1,0,0,0,0],"name":"no_name","customButton":[{"value":0,"text":"PT:W51"},{"value":6,"text":"種:はいたか"},{"value":0,"text":"行先:未実装"}]},{"formation":1775744909314,"id":3604,"speed":0.03957202,"notch":-8,"modelName":"MK683_C","isControlCar":false,"signal":0,"driver":"","passengers":[null,null,null,null,null,null,null,null,null,null,null,null,null,null,null,null,null,null,null,null,null,null,null,null,null,null,null,null,null,null,null,null],"pos":{"x":-14146.5,"y":52.9375,"z":10870.966385372285},"trainStateData":[1,-8,0,0,0,2,1,0,0,0,1,1,0,0,0,0],"name":"no_name","customButton":[{"value":0,"text":"PT:W51"},{"value":6,"text":"種:はいたか"},{"value":0,"text":"行先:未実装"}]},{"formation":1775744909314,"id":3639,"speed":0.03957202,"notch":-8,"modelName":"MK683_B","isControlCar":false,"signal":0,"driver":"","passengers":[null,null,null,null,null,null,null,null,null,null,null,null,null,null,null,null,null,null,null,null,null,null,null,null,null,null,null,null,null,null,null,null],"pos":{"x":-14146.5,"y":52.9375,"z":10890.968237226676},"trainStateData":[1,-8,0,0,0,2,1,0,0,0,1,1,0,0,0,0],"name":"no_name","customButton":[{"value":0,"text":"PT:W51"},{"value":6,"text":"種:はいたか"},{"value":0,"text":"行先:未実装"}]},{"formation":1775744909314,"id":3674,"speed":0.03957202,"notch":1,"modelName":"MK683_A","isControlCar":true,"signal":0,"driver":"mikawa321","passengers":[null,null,null,null,null,null,null,null,null,null,null,null,null,null,null,null,null,null,null,null,null,null,null,null],"pos":{"x":-14146.5,"y":52.9375,"z":10910.97008958771},"trainStateData":[0,1,0,0,0,2,1,0,0,0,0,1,0,0,0,0],"name":"no_name","customButton":[{"value":0,"text":"PT:W51"},{"value":6,"text":"種:はいたか"},{"value":0,"text":"行先:未実装"}]}]}