{"last_update":"2026-04-05T13:24:28Z","data":[{"formation":1775395458526,"id":1266,"speed":0.0,"notch":0,"modelName":"ASTA_ATKtypeH_b1","isControlCar":true,"signal":0,"driver":"","passengers":[null,null,null,null,null,null,null,null],"pos":{"x":-13115.718750720378,"y":66.25,"z":13572.5},"trainStateData":[0,0,0,0,0,0,0,0,0,0,0,0,0,0,0,0],"name":"no_name","customButton":[]},{"formation":1775395461037,"id":1277,"speed":0.0061439998,"notch":2,"modelName":"ASTA_ATKtypeH_b2","isControlCar":true,"signal":0,"driver":"BlockFT","passengers":[null,null,null,null,null,null,null,null,null,null,null,null,null],"pos":{"x":-13127.737673276475,"y":66.25,"z":13572.5},"trainStateData":[0,2,0,0,0,0,0,0,0,0,0,0,0,0,0,0],"name":"no_name","customButton":[]},{"formation":1775395463560,"id":1297,"speed":0.0,"notch":0,"modelName":"ASTA_ATKtypeH_b3","isControlCar":true,"signal":0,"driver":"","passengers":[null,null,null,null,null,null,null,null],"pos":{"x":-13141.50000012666,"y":66.25,"z":13572.5},"trainStateData":[0,0,0,0,0,0,0,0,0,0,0,0,0,0,0,0],"name":"no_name","customButton":[]}]}