{"last_update":"2026-05-27T11:52:45Z","data":[{"formation":1779882504405,"id":756,"speed":1.0808952,"notch":3,"modelName":"KR2001","isControlCar":true,"signal":0,"driver":"eight8143","passengers":[null,null,null,null,null,null,null,null,null,null,null,null,null,null,null,null,null,null,null,null,null,null,null,null,null,null,null,null,null,null,null,null,null,null,null,null,null,null,null,null,null,null,null,null],"pos":{"x":-4069.232447527754,"y":75.25,"z":11924.5},"trainStateData":[0,3,0,0,0,2,0,0,1,27,0,0,0,0,0,0],"name":"no_name","customButton":[{"value":0,"text":"種別"},{"value":0,"text":"行先"},{"value":0,"text":"保安装置(非設)"},{"value":0,"text":"信号場進路"},{"value":0,"text":"入換番線"},{"value":0,"text":"PRC状態"},{"value":0,"text":"進路選択(緑ケ浜)"},{"value":0,"text":"進路選択(鳶島)"}]},{"formation":1779882504405,"id":846,"speed":1.0808952,"notch":-8,"modelName":"KR2005","isControlCar":false,"signal":0,"driver":"","passengers":[null,null,null,null,null,null,null,null,null,null,null,null,null,null,null,null,null,null,null,null,null,null,null,null,null,null,null,null,null,null,null,null,null,null,null,null,null,null,null,null],"pos":{"x":-4049.2324470211147,"y":75.25,"z":11924.5},"trainStateData":[1,-8,0,0,0,2,0,0,1,27,1,0,0,0,0,0],"name":"no_name","customButton":[{"value":0,"text":"種別"},{"value":0,"text":"行先"},{"value":0,"text":"保安装置(非設)"},{"value":0,"text":"信号場進路"},{"value":0,"text":"入換番線"},{"value":0,"text":"PRC状態"},{"value":0,"text":"進路選択(緑ケ浜)"},{"value":0,"text":"進路選択(鳶島)"}]},{"formation":1779882504405,"id":889,"speed":1.0808952,"notch":-8,"modelName":"KR2002","isControlCar":false,"signal":0,"driver":"","passengers":[null,null,null,null,null,null,null,null,null,null,null,null,null,null,null,null,null,null,null,null,null,null,null,null,null,null,null,null,null,null,null,null,null,null,null,null,null,null,null,null],"pos":{"x":-4029.231058542443,"y":75.25,"z":11924.5},"trainStateData":[1,-8,0,0,0,2,0,0,1,27,1,0,0,0,0,0],"name":"no_name","customButton":[{"value":0,"text":"種別"},{"value":0,"text":"行先"},{"value":0,"text":"保安装置(非設)"},{"value":0,"text":"信号場進路"},{"value":0,"text":"入換番線"},{"value":0,"text":"PRC状態"},{"value":0,"text":"進路選択(緑ケ浜)"},{"value":0,"text":"進路選択(鳶島)"}]},{"formation":1779882504405,"id":932,"speed":1.0808952,"notch":-8,"modelName":"KR2002","isControlCar":false,"signal":0,"driver":"","passengers":[null,null,null,null,null,null,null,null,null,null,null,null,null,null,null,null,null,null,null,null,null,null,null,null,null,null,null,null,null,null,null,null,null,null,null,null,null,null,null,null],"pos":{"x":-4009.2296690504927,"y":75.25,"z":11924.5},"trainStateData":[1,-8,0,0,0,2,0,0,1,27,1,0,0,0,0,0],"name":"no_name","customButton":[{"value":0,"text":"種別"},{"value":0,"text":"行先"},{"value":0,"text":"保安装置(非設)"},{"value":0,"text":"信号場進路"},{"value":0,"text":"入換番線"},{"value":0,"text":"PRC状態"},{"value":0,"text":"進路選択(緑ケ浜)"},{"value":0,"text":"進路選択(鳶島)"}]},{"formation":1779882504405,"id":975,"speed":1.0808952,"notch":-8,"modelName":"KR2004","isControlCar":false,"signal":0,"driver":"","passengers":[null,null,null,null,null,null,null,null,null,null,null,null,null,null,null,null,null,null,null,null,null,null,null,null,null,null,null,null,null,null,null,null,null,null,null,null,null,null,null,null],"pos":{"x":-3989.2282805718214,"y":75.25,"z":11924.5},"trainStateData":[1,-8,0,0,0,2,0,0,1,27,1,0,0,0,0,0],"name":"no_name","customButton":[{"value":0,"text":"種別"},{"value":0,"text":"行先"},{"value":0,"text":"保安装置(非設)"},{"value":0,"text":"信号場進路"},{"value":0,"text":"入換番線"},{"value":0,"text":"PRC状態"},{"value":0,"text":"進路選択(緑ケ浜)"},{"value":0,"text":"進路選択(鳶島)"}]},{"formation":1779882504405,"id":1018,"speed":1.0808952,"notch":-8,"modelName":"KR2002","isControlCar":false,"signal":0,"driver":"","passengers":[null,null,null,null,null,null,null,null,null,null,null,null,null,null,null,null,null,null,null,null,null,null,null,null,null,null,null,null,null,null,null,null,null,null,null,null,null,null,null,null],"pos":{"x":-3969.226734590984,"y":75.25,"z":11924.5},"trainStateData":[1,-8,0,0,0,2,0,0,1,27,1,0,0,0,0,0],"name":"no_name","customButton":[{"value":0,"text":"種別"},{"value":0,"text":"行先"},{"value":0,"text":"保安装置(非設)"},{"value":0,"text":"信号場進路"},{"value":0,"text":"入換番線"},{"value":0,"text":"PRC状態"},{"value":0,"text":"進路選択(緑ケ浜)"},{"value":0,"text":"進路選択(鳶島)"}]},{"formation":1779882504405,"id":1061,"speed":1.0808952,"notch":-8,"modelName":"KR2005","isControlCar":false,"signal":0,"driver":"","passengers":[null,null,null,null,null,null,null,null,null,null,null,null,null,null,null,null,null,null,null,null,null,null,null,null,null,null,null,null,null,null,null,null,null,null,null,null,null,null,null,null],"pos":{"x":-3949.225134713245,"y":75.25,"z":11924.5},"trainStateData":[1,-8,0,0,0,2,0,0,1,27,1,0,0,0,0,0],"name":"no_name","customButton":[{"value":0,"text":"種別"},{"value":0,"text":"行先"},{"value":0,"text":"保安装置(非設)"},{"value":0,"text":"信号場進路"},{"value":0,"text":"入換番線"},{"value":0,"text":"PRC状態"},{"value":0,"text":"進路選択(緑ケ浜)"},{"value":0,"text":"進路選択(鳶島)"}]},{"formation":1779882504405,"id":1104,"speed":1.0808952,"notch":-8,"modelName":"KR2003","isControlCar":false,"signal":0,"driver":"","passengers":[null,null,null,null,null,null,null,null,null,null,null,null,null,null,null,null,null,null,null,null,null,null,null,null,null,null,null,null,null,null,null,null,null,null,null,null,null,null,null,null,null,null,null,null],"pos":{"x":-3929.223696565647,"y":75.25,"z":11924.5},"trainStateData":[1,-8,0,0,0,2,0,0,1,27,1,0,0,0,0,0],"name":"no_name","customButton":[{"value":0,"text":"種別"},{"value":0,"text":"行先"},{"value":0,"text":"保安装置(非設)"},{"value":0,"text":"信号場進路"},{"value":0,"text":"入換番線"},{"value":0,"text":"PRC状態"},{"value":0,"text":"進路選択(緑ケ浜)"},{"value":0,"text":"進路選択(鳶島)"}]}]}