{"last_update":"2026-04-03T05:35:09Z","data":[{"formation":1775193769106,"id":4784,"speed":1.2004251,"notch":-8,"modelName":"6R_EF210-1","isControlCar":false,"signal":0,"driver":"","passengers":[null,null],"pos":{"x":-17122.997685258408,"y":76.25,"z":-6892.418442976869},"trainStateData":[1,-8,0,0,1,0,0,0,0,1,1,0,0,0,0,0],"name":"no_name","customButton":[]},{"formation":1775193769106,"id":4791,"speed":1.2004251,"notch":-8,"modelName":"6R_EF210-1","isControlCar":false,"signal":0,"driver":"","passengers":[null,null],"pos":{"x":-17111.485957987785,"y":76.25,"z":-6878.085394014724},"trainStateData":[1,-8,0,0,1,0,0,0,0,1,1,0,0,0,0,0],"name":"no_name","customButton":[]},{"formation":1775193769106,"id":4799,"speed":1.2004251,"notch":-8,"modelName":"6R_EF210-1","isControlCar":false,"signal":0,"driver":"","passengers":[null,null],"pos":{"x":-17100.86025325313,"y":76.25,"z":-6863.090979880566},"trainStateData":[0,-8,0,0,2,0,0,0,0,1,1,0,0,0,0,0],"name":"no_name","customButton":[]},{"formation":1775193769106,"id":4805,"speed":1.2004251,"notch":-8,"modelName":"6R_EF210-1","isControlCar":false,"signal":0,"driver":"","passengers":[null,null],"pos":{"x":-17091.181721744888,"y":76.25,"z":-6847.471304817461},"trainStateData":[0,-8,0,0,2,0,0,0,0,1,1,0,0,0,0,0],"name":"no_name","customButton":[]},{"formation":1775193769106,"id":4810,"speed":1.2004251,"notch":-8,"modelName":"6R_EF210-1","isControlCar":false,"signal":0,"driver":"","passengers":[null,null],"pos":{"x":-17082.492194160128,"y":76.25,"z":-6831.283554695885},"trainStateData":[0,-8,0,0,2,0,0,0,0,1,1,0,0,0,0,0],"name":"no_name","customButton":[]},{"formation":1775193769106,"id":4815,"speed":1.2004251,"notch":5,"modelName":"6R_EF210-1","isControlCar":true,"signal":0,"driver":"Ga_libe4104","passengers":["Nairo716",null],"pos":{"x":-17074.782173869113,"y":76.25,"z":-6814.602292170146},"trainStateData":[0,5,0,0,2,0,0,0,0,1,0,0,0,0,0,0],"name":"no_name","customButton":[]}]}