{"last_update":"2026-06-13T01:58:05Z","data":[{"formation":1781315147215,"id":898,"speed":0.11887448,"notch":-8,"modelName":"Hoshikage3510_Tc2","isControlCar":false,"signal":0,"driver":"","passengers":[null,null,null,null,null,null,null,null,null,null,null,null,null,null,null,null,null,null,null,null,null,null,null,null,null,null,null,null],"pos":{"x":23415.272176324983,"y":66.2775522172451,"z":-6171.940020370642},"trainStateData":[1,-8,0,0,0,2,0,0,4,0,1,0,0,0,0,0],"name":"no_name","customButton":[]},{"formation":1781315147215,"id":929,"speed":0.11887448,"notch":-8,"modelName":"Hoshikage3510_T","isControlCar":false,"signal":0,"driver":"","passengers":[null,null,null,null,null,null,null,null,null,null,null,null,null,null,null,null,null,null,null,null,null,null,null,null,null,null,null,null],"pos":{"x":23398.02817914758,"y":66.30356783792377,"z":-6161.80317663029},"trainStateData":[0,-8,0,0,0,2,0,0,4,0,1,0,0,0,0,0],"name":"no_name","customButton":[]},{"formation":1781315147215,"id":962,"speed":0.11887448,"notch":1,"modelName":"Hoshikage3510_Mc","isControlCar":true,"signal":0,"driver":"eight8143","passengers":[null,null,null,null,null,null,null,null,null,null,null,null,null,null,null,null,null,null,null,null,null,null,null,null,null,null,null,null],"pos":{"x":23380.514247269883,"y":66.32919518649578,"z":-6152.1411811532325},"trainStateData":[0,1,0,0,0,2,0,0,4,0,0,0,0,0,0,0],"name":"no_name","customButton":[]},{"formation":1781315812725,"id":1180,"speed":0.0,"notch":-4,"modelName":"Hoshikage3500_Tc","isControlCar":true,"signal":0,"driver":"","passengers":[null,null,null,null,null,null,null,null,null,null,null,null,null,null,null,null,null,null,null,null,null,null,null,null,null,null,null,null],"pos":{"x":23416.580637118055,"y":66.272868655622,"z":-6177.019567248051},"trainStateData":[0,-4,0,0,2,2,0,0,2,0,0,0,0,0,0,0],"name":"no_name","customButton":[]},{"formation":1781315812725,"id":1211,"speed":0.0,"notch":-8,"modelName":"Hoshikage3500_Mc2","isControlCar":false,"signal":0,"driver":"","passengers":[null,null,null,null,null,null,null,null,null,null,null,null,null,null,null,null,null,null,null,null,null,null,null,null,null,null,null,null],"pos":{"x":23399.25248076757,"y":66.29937119781971,"z":-6167.026592974928},"trainStateData":[1,-8,0,0,1,2,0,0,2,0,1,0,0,0,0,0],"name":"no_name","customButton":[]}]}